fastzdp_redis/__init__.py
fastzdp_redis/client.py
fastzdp_redis/string.py
fastzdp_redis-0.1.0.dist-info/LICENSE
fastzdp_redis-0.1.0.dist-info/METADATA
fastzdp_redis-0.1.0.dist-info/WHEEL
fastzdp_redis-0.1.0.dist-info/RECORD
