Metadata-Version: 2.1
Name: fastzdp-redis
Version: 0.1.0
Summary: FastZDP框架体系下操作Redis的国产框架, 低代码开发, 简单易用, 提高企业项目开发效率
Author: 张大鹏
Author-email: 1156956636@qq.com
Requires-Python: >=3.12,<4.0
Classifier: Programming Language :: Python :: 3
Classifier: Programming Language :: Python :: 3.12
Requires-Dist: redis[hiredis] (>=5.0.8,<6.0.0)
